project/m4/rtl/compute_core.sv
/*
 * Module: compute_core
 *
 * Purpose:
 *   Simple INT8 multiply-accumulate compute core for the HW4AI M4 project.
 *   This represents the dominant GEMM/MAC operation from the project.
 *
 * Ports:
 *   clk    : input,  1 bit   - clock
 *   rst    : input,  1 bit   - active-high synchronous reset
 *   valid  : input,  1 bit   - when high, input a and b are accumulated
 *   a      : input,  8 bits  - signed INT8 operand A
 *   b      : input,  8 bits  - signed INT8 operand B
 *   out    : output, 32 bits - signed accumulated MAC result
 *
 * Clocking:
 *   Single clock domain using clk.
 *
 * Reset:
 *   Active-high synchronous reset. When rst = 1, out is cleared to 0.
 */

module compute_core (
    input  logic clk,
    input  logic rst,
    input  logic valid,
    input  logic signed [7:0] a,
    input  logic signed [7:0] b,
    output logic signed [31:0] out
);

    logic signed [15:0] product;

    assign product = a * b;

    always_ff @(posedge clk) begin
        if (rst) begin
            out <= 32'sd0;
        end else if (valid) begin
            out <= out + {{16{product[15]}}, product};
        end
    end

endmodule

project/m2/tb/tb_compute_core.sv
`timescale 1ns/1ps

module tb_compute_core;

    logic clk;
    logic rst;
    logic valid;
    logic signed [7:0] a;
    logic signed [7:0] b;
    logic signed [31:0] out;

    logic signed [31:0] expected;

    compute_core dut (
        .clk(clk),
        .rst(rst),
        .valid(valid),
        .a(a),
        .b(b),
        .out(out)
    );

    always #5 clk = ~clk;

    initial begin
        $dumpfile("project/m2/sim/compute_core.vcd");
        $dumpvars(0, tb_compute_core);
        clk = 0;
        rst = 1;
        valid = 0;
        a = 0;
        b = 0;
        expected = 0;

        #10;
        rst = 0;

        // Representative INT8 MAC/GEMM-style input sequence
        valid = 1;

        a = 8'sd3;   b = 8'sd4;   expected = expected + (3 * 4);    #10;
        a = -8'sd5;  b = 8'sd2;   expected = expected + (-5 * 2);   #10;
        a = 8'sd7;   b = -8'sd3;  expected = expected + (7 * -3);   #10;
        a = -8'sd8;  b = -8'sd4;  expected = expected + (-8 * -4);  #10;

        valid = 0;
        #10;

        if (out === expected) begin
            $display("PASS: compute_core output matched expected value.");
            $display("Expected = %0d, DUT Output = %0d", expected, out);
        end else begin
            $display("FAIL: compute_core output mismatch.");
            $display("Expected = %0d, DUT Output = %0d", expected, out);
        end

        $finish;
    end

endmodule

project/m2/sim/compute_core.vcd
$date
	Thu Apr 30 18:41:58 2026
$end
$version
	Icarus Verilog
$end
$timescale
	1ps
$end
$scope module tb_compute_core $end
$var wire 32 ! out [31:0] $end
$var reg 8 " a [7:0] $end
$var reg 8 # b [7:0] $end
$var reg 1 $ clk $end
$var reg 32 % expected [31:0] $end
$var reg 1 & rst $end
$var reg 1 ' valid $end
$scope module dut $end
$var wire 8 ( a [7:0] $end
$var wire 8 ) b [7:0] $end
$var wire 1 $ clk $end
$var wire 1 & rst $end
$var wire 1 ' valid $end
$var wire 16 * product [15:0] $end
$var reg 32 + out [31:0] $end
$upscope $end
$upscope $end
$enddefinitions $end
#0
$dumpvars
bx +
b0 *
b0 )
b0 (
0'
1&
b0 %
0$
b0 #
b0 "
bx !
$end
#5000
b0 !
b0 +
1$
#10000
0$
b1100 %
b1100 *
b100 #
b100 )
b11 "
b11 (
1'
0&
#15000
b1100 !
b1100 +
1$
#20000
0$
b10 %
b10 #
b10 )
b1111111111110110 *
b11111011 "
b11111011 (
#25000
b10 !
b10 +
1$
#30000
0$
b11111111111111111111111111101101 %
b11111101 #
b11111101 )
b1111111111101011 *
b111 "
b111 (
#35000
b11111111111111111111111111101101 !
b11111111111111111111111111101101 +
1$
#40000
0$
b1101 %
b11111100 #
b11111100 )
b100000 *
b11111000 "
b11111000 (
#45000
b1101 !
b1101 +
1$
#50000
0$
0'
