codefest/cf04/hdl/mac_correct.v
module mac (
    input  logic clk,
    input  logic rst,
    input  logic signed [7:0] a,
    input  logic signed [7:0] b,
    output logic signed [31:0] out
);

    logic signed [31:0] product_ext;

    assign product_ext = $signed(a) * $signed(b);

    always_ff @(posedge clk) begin
        if (rst) begin
            out <= 32'sd0;
        end else begin
            // 32-bit signed accumulation with wraparound
            out <= out + product_ext;
        end
    end

endmodule

codefest/cf04/hdl/mac_tb.v
`timescale 1ns/1ps

module mac_tb;

    logic clk;
    logic rst;
    logic signed [7:0] a;
    logic signed [7:0] b;
    logic signed [31:0] out;

    mac dut (
        .clk(clk),
        .rst(rst),
        .a(a),
        .b(b),
        .out(out)
    );

    // 10 ns clock period
    always #5 clk = ~clk;

    initial begin
        $dumpfile("mac_tb.vcd");
        $dumpvars(0, mac_tb);

        clk = 0;
        rst = 1;
        a = 0;
        b = 0;

        // Apply reset
        @(posedge clk);
        #1;
        if (out !== 32'sd0)
            $display("FAIL: Reset output expected 0, got %0d", out);
        else
            $display("PASS: Reset output = %0d", out);

        // Release reset
        rst = 0;

        // Apply a = 3, b = 4 for 3 cycles
        a = 8'sd3;
        b = 8'sd4;

        @(posedge clk);
        #1;
        $display("Cycle 1: a=%0d b=%0d out=%0d", a, b, out);

        @(posedge clk);
        #1;
        $display("Cycle 2: a=%0d b=%0d out=%0d", a, b, out);

        @(posedge clk);
        #1;
        $display("Cycle 3: a=%0d b=%0d out=%0d", a, b, out);

        // Assert reset again
        rst = 1;
        @(posedge clk);
        #1;
        $display("After reset: out=%0d", out);

        // Release reset and apply a = -5, b = 2 for 2 cycles
        rst = 0;
        a = -8'sd5;
        b = 8'sd2;

        @(posedge clk);
        #1;
        $display("Cycle 4: a=%0d b=%0d out=%0d", a, b, out);

        @(posedge clk);
        #1;
        $display("Cycle 5: a=%0d b=%0d out=%0d", a, b, out);

        $finish;
    end

endmodule

codefest/cf04/hdl/mac_tb.vcd
$date
	Sun Apr 26 20:08:13 2026
$end
$version
	Icarus Verilog
$end
$timescale
	1ps
$end
$scope module mac_tb $end
$var wire 32 ! out [31:0] $end
$var reg 8 " a [7:0] $end
$var reg 8 # b [7:0] $end
$var reg 1 $ clk $end
$var reg 1 % rst $end
$scope module dut $end
$var wire 8 & a [7:0] $end
$var wire 8 ' b [7:0] $end
$var wire 1 $ clk $end
$var wire 1 % rst $end
$var wire 32 ( product_ext [31:0] $end
$var reg 32 ) out [31:0] $end
$upscope $end
$upscope $end
$enddefinitions $end
#0
$dumpvars
bx )
b0 (
b0 '
b0 &
1%
0$
b0 #
b0 "
bx !
$end
#5000
b0 !
b0 )
1$
#6000
b1100 (
b100 #
b100 '
b11 "
b11 &
0%
#10000
0$
#15000
b1100 !
b1100 )
1$
#20000
0$
#25000
b11000 !
b11000 )
1$
#30000
0$
#35000
b100100 !
b100100 )
1$
#36000
1%
#40000
0$
#45000
b0 !
b0 )
1$
#46000
b10 #
b10 '
b11111111111111111111111111110110 (
b11111011 "
b11111011 &
0%
#50000
0$
#55000
b11111111111111111111111111110110 !
b11111111111111111111111111110110 )
1$
#60000
0$
#65000
b11111111111111111111111111101100 !
b11111111111111111111111111101100 )
1$
