project/m4/rtl/compute_core.sv
/*
 * Module: compute_core
 *
 * Purpose:
 *   Simple INT8 multiply-accumulate compute core for the HW4AI M4 project.
 *   This represents the dominant GEMM/MAC operation from the project.
 *
 * Ports:
 *   clk    : input,  1 bit   - clock
 *   rst    : input,  1 bit   - active-high synchronous reset
 *   valid  : input,  1 bit   - when high, input a and b are accumulated
 *   a      : input,  8 bits  - signed INT8 operand A
 *   b      : input,  8 bits  - signed INT8 operand B
 *   out    : output, 32 bits - signed accumulated MAC result
 *
 * Clocking:
 *   Single clock domain using clk.
 *
 * Reset:
 *   Active-high synchronous reset. When rst = 1, out is cleared to 0.
 */

module compute_core (
    input  logic clk,
    input  logic rst,
    input  logic valid,
    input  logic signed [7:0] a,
    input  logic signed [7:0] b,
    output logic signed [31:0] out
);

    logic signed [15:0] product;

    assign product = a * b;

    always_ff @(posedge clk) begin
        if (rst) begin
            out <= 32'sd0;
        end else if (valid) begin
            out <= out + {{16{product[15]}}, product};
        end
    end

endmodule

project/m4/rtl/interface_ctrl.sv
/*
 * Module: interface_ctrl
 *
 * Purpose:
 *   Memory-mapped interface to control compute_core.
 *
 * Protocol:
 *   Simple valid/ready handshake (always-ready).
 *
 * Register Map:
 *   0x00 : operand A
 *   0x04 : operand B
 *   0x08 : control (bit[0] = start)
 *   0x0C : result
 *
 * Ports:
 *   clk        : clock
 *   rst        : active-high synchronous reset
 *   valid      : request valid
 *   ready      : always ready
 *   write      : write enable
 *   addr       : address
 *   wdata      : write data
 *   rdata      : read data
 *   core_valid : trigger to compute core
 *   core_a     : operand A
 *   core_b     : operand B
 *   core_out   : result from compute core
 */



module interface_ctrl (
    input  wire clk,
    input  wire rst,

    input  wire valid,
    output wire ready,
    input  wire write,
    input  wire [7:0] addr,
    input  wire [31:0] wdata,
    output reg  [31:0] rdata,

    output reg  core_valid,
    output reg  signed [7:0] core_a,
    output reg  signed [7:0] core_b,
    input  wire signed [31:0] core_out
);

    assign ready = 1'b1;

    always @(posedge clk) begin
        if (rst) begin
            core_a     <= 0;
            core_b     <= 0;
            core_valid <= 0;
            rdata      <= 0;
        end else begin
            core_valid <= 0;

            if (valid && ready) begin
                if (write) begin
                    case (addr)
                        8'h00: core_a <= wdata[7:0];
                        8'h04: core_b <= wdata[7:0];
                        8'h08: begin
                            if (wdata[0])
                                core_valid <= 1;
                        end
                    endcase
                end else begin
                    case (addr)
                        8'h00: rdata <= {{24{core_a[7]}}, core_a};
                        8'h04: rdata <= {{24{core_b[7]}}, core_b};
                        8'h0C: rdata <= core_out;
                        default: rdata <= 0;
                    endcase
                end
            end
        end
    end

endmodule

project/m4/rtl/top.sv
/*
 * Module: top
 *
 * Purpose:
 *   M3 integrated top module connecting the memory-mapped interface
 *   to the INT8 MAC compute core.
 *
 * Ports:
 *   clk   : input,  1 bit   - clock
 *   rst   : input,  1 bit   - active-high reset
 *   valid : input,  1 bit   - host request valid
 *   ready : output, 1 bit   - interface ready
 *   write : input,  1 bit   - host write enable
 *   addr  : input,  8 bits  - memory-mapped address
 *   wdata : input,  32 bits - host write data
 *   rdata : output, 32 bits - host read data
 *
 * Glue logic:
 *   No extra FIFO or clock-domain crossing is used.
 *   The interface directly drives core_valid, core_a, and core_b.
 *   The compute result core_out is returned back through the interface.
 */

module top (
    input  wire clk,
    input  wire rst,

    input  wire valid,
    output wire ready,
    input  wire write,

    input  wire [7:0]  addr,
    input  wire [31:0] wdata,
    output wire [31:0] rdata
);

    wire core_valid;
    wire signed [7:0] core_a;
    wire signed [7:0] core_b;
    wire signed [31:0] core_out;

    interface_ctrl u_interface (
        .clk(clk),
        .rst(rst),
        .valid(valid),
        .ready(ready),
        .write(write),
        .addr(addr),
        .wdata(wdata),
        .rdata(rdata),
        .core_valid(core_valid),
        .core_a(core_a),
        .core_b(core_b),
        .core_out(core_out)
    );

    compute_core u_compute (
        .clk(clk),
        .rst(rst),
        .valid(core_valid),
        .a(core_a),
        .b(core_b),
        .out(core_out)
    );

endmodule

project/m3/tb/tb_top.sv
`timescale 1ns/1ps

module tb_top;

    logic clk;
    logic rst;
    logic valid;
    logic ready;
    logic write;
    logic [7:0] addr;
    logic [31:0] wdata;
    logic [31:0] rdata;

    integer row, col, k;
    integer expected;
    integer errors;

    top dut (
        .clk(clk),
        .rst(rst),
        .valid(valid),
        .ready(ready),
        .write(write),
        .addr(addr),
        .wdata(wdata),
        .rdata(rdata)
    );

    always #5 clk = ~clk;

    task reset_core;
        begin
            @(negedge clk);
            rst = 1;
            valid = 0;
            write = 0;
            addr = 0;
            wdata = 0;
            repeat (2) @(negedge clk);
            rst = 0;
        end
    endtask

    task host_write(input [7:0] write_addr, input [31:0] write_data);
        begin
            @(negedge clk);
            valid = 1'b1;
            write = 1'b1;
            addr  = write_addr;
            wdata = write_data;

            @(negedge clk);
            valid = 1'b0;
            write = 1'b0;
            addr  = 8'h00;
            wdata = 32'h00000000;
        end
    endtask

    task host_read(input [7:0] read_addr);
        begin
            @(negedge clk);
            valid = 1'b1;
            write = 1'b0;
            addr  = read_addr;

            @(negedge clk);
            valid = 1'b0;
            addr  = 8'h00;
        end
    endtask

    initial begin
        $dumpfile("sim/final_waveform.vcd");
        $dumpvars(0, tb_top);

        clk = 0;
        rst = 1;
        valid = 0;
        write = 0;
        addr = 0;
        wdata = 0;
        errors = 0;

        repeat (3) @(posedge clk);
        rst = 0;

        /*
         * Full 16x16 GEMM-style test.
         *
         * For each output C[row][col], the test performs:
         * C[row][col] = sum over k=0..15 of A[row][k] * B[k][col]
         *
         * Matrix values are generated deterministically:
         * A[row][k] = row + k + 1
         * B[k][col] = k + col + 1
         *
         * Each multiply-accumulate is sent through the host interface.
         * The testbench never directly drives compute_core ports.
         */

        for (row = 0; row < 16; row = row + 1) begin
            for (col = 0; col < 16; col = col + 1) begin

                reset_core();
                expected = 0;

                for (k = 0; k < 16; k = k + 1) begin
                    host_write(8'h00, row + k + 1);
                    host_write(8'h04, k + col + 1);
                    host_write(8'h08, 32'd1);

                    expected = expected + ((row + k + 1) * (k + col + 1));

                    repeat (1) @(posedge clk);
                end

                repeat (2) @(posedge clk);
                host_read(8'h0C);
                @(posedge clk);

                if ($signed(rdata) !== expected) begin
                    $display("FAIL: C[%0d][%0d] expected=%0d got=%0d",
                             row, col, expected, $signed(rdata));
                    errors = errors + 1;
                end
            end
        end

        if (errors == 0) begin
            $display("PASS: Full 16x16 GEMM-style host-interface-compute-host test passed");
            $display("Checked 256 output elements with 16 MACs each = 4096 MAC operations");
        end else begin
            $display("FAIL: Full 16x16 GEMM-style test failed with %0d errors", errors);
        end

        #20;
        $finish;
    end

endmodule

project/m3/sim/cosim_waveform.vcd
$date
	Thu May 21 19:04:21 2026
$end
$version
	Icarus Verilog
$end
$timescale
	1ps
$end
$scope module tb_top $end
$var wire 1 ! ready $end
$var wire 32 " rdata [31:0] $end
$var reg 8 # addr [7:0] $end
$var reg 1 $ clk $end
$var reg 1 % rst $end
$var reg 1 & valid $end
$var reg 32 ' wdata [31:0] $end
$var reg 1 ( write $end
$var integer 32 ) col [31:0] $end
$var integer 32 * errors [31:0] $end
$var integer 32 + expected [31:0] $end
$var integer 32 , k [31:0] $end
$var integer 32 - row [31:0] $end
$scope module dut $end
$var wire 8 . addr [7:0] $end
$var wire 1 $ clk $end
$var wire 1 ! ready $end
$var wire 1 % rst $end
$var wire 1 & valid $end
$var wire 32 / wdata [31:0] $end
$var wire 1 ( write $end
$var wire 32 0 rdata [31:0] $end
$var wire 1 1 core_valid $end
$var wire 32 2 core_out [31:0] $end
$var wire 8 3 core_b [7:0] $end
$var wire 8 4 core_a [7:0] $end
$scope module u_compute $end
$var wire 1 $ clk $end
$var wire 1 % rst $end
$var wire 1 1 valid $end
$var wire 16 5 product [15:0] $end
$var wire 8 6 b [7:0] $end
$var wire 8 7 a [7:0] $end
$var reg 32 8 out [31:0] $end
$upscope $end
$scope module u_interface $end
$var wire 8 9 addr [7:0] $end
$var wire 1 $ clk $end
$var wire 32 : core_out [31:0] $end
$var wire 1 ! ready $end
$var wire 1 % rst $end
$var wire 1 & valid $end
$var wire 32 ; wdata [31:0] $end
$var wire 1 ( write $end
$var reg 8 < core_a [7:0] $end
$var reg 8 = core_b [7:0] $end
$var reg 1 1 core_valid $end
$var reg 32 > rdata [31:0] $end
$upscope $end
$upscope $end
$scope task host_read $end
$var reg 8 ? read_addr [7:0] $end
$upscope $end
$scope task host_write $end
$var reg 8 @ write_addr [7:0] $end
$var reg 32 A write_data [31:0] $end
$upscope $end
$scope task reset_core $end
$upscope $end
$upscope $end
$enddefinitions $end
#0
$dumpvars
bx A
bx @
bx ?
bx >
bx =
bx <
b0 ;
bx :
b0 9
bx 8
bx 7
bx 6
bx 5
bx 4
bx 3
bx 2
x1
bx 0
b0 /
b0 .
bx -
bx ,
bx +
b0 *
bx )
0(
b0 '
0&
1%
0$
b0 #
bx "
1!
$end
#5000
b0 "
b0 0
b0 >
01
b0 5
b0 3
b0 6
b0 =
b0 4
b0 7
b0 <
b0 2
b0 8
b0 :
1$
#10000
0$
#15000
1$
#20000
0$
#25000
b0 )
b0 -
0%
1$
#30000
1%
0$
#35000
1$
#40000
0$
#45000
1$
#50000
b1 A
b0 @
b0 ,
b0 +
0%
0$
#55000
1$
#60000
b1 '
b1 /
b1 ;
1(
1&
0$
#65000
b1 4
b1 7
b1 <
1$
#70000
b100 @
b0 '
b0 /
b0 ;
0(
0&
0$
#75000
1$
#80000
b1 '
b1 /
b1 ;
b100 #
b100 .
b100 9
1(
1&
0$
#85000
b1 5
b1 3
b1 6
b1 =
1$
#90000
b1000 @
b0 '
b0 /
b0 ;
b0 #
b0 .
b0 9
0(
0&
0$
#95000
1$
#100000
b1 '
b1 /
b1 ;
b1000 #
b1000 .
b1000 9
1(
1&
0$
#105000
11
1$
#110000
b1 +
b0 '
b0 /
b0 ;
b0 #
b0 .
b0 9
0(
0&
0$
#115000
b1 2
b1 8
b1 :
01
b10 A
b0 @
b1 ,
1$
#120000
b10 '
b10 /
b10 ;
1(
1&
0$
#125000
b10 5
b10 4
b10 7
b10 <
1$
#130000
b100 @
b0 '
b0 /
b0 ;
0(
0&
0$
#135000
1$
#140000
b10 '
b10 /
b10 ;
b100 #
b100 .
b100 9
1(
1&
0$
#145000
b100 5
b10 3
b10 6
b10 =
1$
#150000
b1 A
b1000 @
b0 '
b0 /
b0 ;
b0 #
b0 .
b0 9
0(
0&
0$
#155000
1$
#160000
b1 '
b1 /
b1 ;
b1000 #
b1000 .
b1000 9
1(
1&
0$
#165000
11
1$
#170000
b101 +
b0 '
b0 /
b0 ;
b0 #
b0 .
b0 9
0(
0&
0$
#175000
b101 2
b101 8
b101 :
01
b11 A
b0 @
b10 ,
1$
#180000
b11 '
b11 /
b11 ;
1(
1&
0$
#185000
b110 5
b11 4
b11 7
b11 <
1$
#190000
b100 @
b0 '
b0 /
b0 ;
0(
0&
0$
#195000
1$
#200000
b11 '
b11 /
b11 ;
b100 #
b100 .
b100 9
1(
1&
0$
#205000
b1001 5
b11 3
b11 6
b11 =
1$
#210000
b1 A
b1000 @
b0 '
b0 /
b0 ;
b0 #
b0 .
b0 9
0(
0&
0$
#215000
1$
#220000
b1 '
b1 /
b1 ;
b1000 #
b1000 .
b1000 9
1(
1&
0$
#225000
11
1$
#230000
b1110 +
b0 '
b0 /
b0 ;
b0 #
b0 .
b0 9
0(
0&
0$
#235000
b1110 2
b1110 8
b1110 :
01
b100 A
b0 @
b11 ,
1$
#240000
b100 '
b100 /
b100 ;
1(
1&
0$
#245000
b1100 5
b100 4
b100 7
b100 <
1$
#250000
b100 @
b0 '
b0 /
b0 ;
0(
0&
0$
#255000
1$
#260000
b100 '
b100 /
b100 ;
b100 #
b100 .
b100 9
1(
1&
0$
#265000
b10000 5
b100 3
b100 6
b100 =
1$
#270000
b1 A
b1000 @
b0 '
b0 /
b0 ;
b0 #
b0 .
b0 9
0(
0&
0$
#275000
1$
#280000
b1 '
b1 /
b1 ;
b1000 #
b1000 .
b1000 9
1(
1&
0$
#285000
11
1$
#290000
b11110 +
b0 '
b0 /
b0 ;
b0 #
b0 .
b0 9
0(
0&
0$
#295000
b11110 2
b11110 8
b11110 :
01
b101 A
b0 @
b100 ,
1$
#300000
b101 '
b101 /
b101 ;
1(
1&
0$
#305000
b10100 5
b101 4
b101 7
b101 <
1$
#310000
b100 @
b0 '
b0 /
b0 ;
0(
0&
0$
#315000
1$
#320000
b101 '
b101 /
b101 ;
b100 #
b100 .
b100 9
1(
1&
0$
#325000
b11001 5
b101 3
b101 6
b101 =
1$
#330000
b1 A
b1000 @
b0 '
b0 /
b0 ;
b0 #
b0 .
b0 9
0(
0&
0$
#335000
1$
#340000
b1 '
b1 /
b1 ;
b1000 #
b1000 .
b1000 9
1(
1&
0$
#345000
11
1$
#350000
b110111 +
b0 '
b0 /
b0 ;
b0 #
b0 .
b0 9
0(
0&
0$
#355000
b110111 2
b110111 8
b110111 :
01
b110 A
b0 @
b101 ,
1$
#360000
b110 '
b110 /
b110 ;
1(
1&
0$
#365000
b11110 5
b110 4
b110 7
b110 <
1$
#370000
b100 @
b0 '
b0 /
b0 ;
0(
0&
0$
#375000
1$
#380000
b110 '
b110 /
b110 ;
b100 #
b100 .
b100 9
1(
1&
0$
#385000
b100100 5
b110 3
b110 6
b110 =
1$
#390000
b1 A
b1000 @
b0 '
b0 /
b0 ;
b0 #
b0 .
b0 9
0(
0&
0$
#395000
1$
#400000
b1 '
b1 /
b1 ;
b1000 #
b1000 .
b1000 9
1(
1&
0$
#405000
11
1$
#410000
b1011011 +
b0 '
b0 /
b0 ;
b0 #
b0 .
b0 9
0(
0&
0$
#415000
b1011011 2
b1011011 8
b1011011 :
01
b111 A
b0 @
b110 ,
1$
#420000
b111 '
b111 /
b111 ;
1(
1&
0$
#425000
b101010 5
b111 4
b111 7
b111 <
1$
#430000
b100 @
b0 '
b0 /
b0 ;
0(
0&
0$
#435000
1$
#440000
b111 '
b111 /
b111 ;
b100 #
b100 .
b100 9
1(
1&
0$
#445000
b110001 5
b111 3
b111 6
b111 =
1$
#450000
b1 A
b1000 @
b0 '
b0 /
b0 ;
b0 #
b0 .
b0 9
0(
0&
0$
#455000
1$
#460000
b1 '
b1 /
b1 ;
b1000 #
b1000 .
b1000 9
1(
1&
0$
#465000
11
1$
#470000
b10001100 +
b0 '
b0 /
b0 ;
b0 #
b0 .
b0 9
0(
0&
0$
#475000
b10001100 2
b10001100 8
b10001100 :
01
b1000 A
b0 @
b111 ,
1$
#480000
b1000 '
b1000 /
b1000 ;
1(
1&
0$
#485000
b111000 5
b1000 4
b1000 7
b1000 <
1$
#490000
b100 @
b0 '
b0 /
b0 ;
0(
0&
0$
#495000
1$
#500000
b1000 '
b1000 /
b1000 ;
b100 #
b100 .
b100 9
1(
1&
0$
#505000
b1000000 5
b1000 3
b1000 6
b1000 =
1$
#510000
b1 A
b1000 @
b0 '
b0 /
b0 ;
b0 #
b0 .
b0 9
0(
0&
0$
#515000
1$
#520000
b1 '
b1 /
b1 ;
b1000 #
b1000 .
b1000 9
1(
1&
0$
#525000
11
1$
#530000
b11001100 +
b0 '
b0 /
b0 ;
b0 #
b0 .
b0 9
0(
0&
0$
#535000
b11001100 2
b11001100 8
b11001100 :
01
b1001 A
b0 @
b1000 ,
1$
#540000
b1001 '
b1001 /
b1001 ;
1(
1&
0$
#545000
b1001000 5
b1001 4
b1001 7
b1001 <
1$
#550000
b100 @
b0 '
b0 /
b0 ;
0(
0&
0$
#555000
1$
#560000
b1001 '
b1001 /
b1001 ;
b100 #
b100 .
b100 9
1(
1&
0$
#565000
b1010001 5
b1001 3
b1001 6
b1001 =
1$
#570000
b1 A
b1000 @
b0 '
b0 /
b0 ;
b0 #
b0 .
b0 9
0(
0&
0$
#575000
1$
#580000
b1 '
b1 /
b1 ;
b1000 #
b1000 .
b1000 9
1(
1&
0$
#585000
11
1$
#590000
b100011101 +
b0 '
b0 /
b0 ;
b0 #
b0 .
b0 9
0(
0&
0$
#595000
b100011101 2
b100011101 8
b100011101 :
01
b1010 A
b0 @
b1001 ,
1$
#600000
b1010 '
b1010 /
b1010 ;
1(
1&
0$
#605000
b1011010 5
b1010 4
b1010 7
b1010 <
1$
#610000
b100 @
b0 '
b0 /
b0 ;
0(
0&
0$
#615000
1$
#620000
b1010 '
b1010 /
b1010 ;
b100 #
b100 .
b100 9
1(
1&
0$
#625000
b1100100 5
b1010 3
b1010 6
b1010 =
1$
#630000
b1 A
b1000 @
b0 '
b0 /
b0 ;
b0 #
b0 .
b0 9
0(
0&
0$
#635000
1$
#640000
b1 '
b1 /
b1 ;
b1000 #
b1000 .
b1000 9
1(
1&
0$
#645000
11
1$
#650000
b110000001 +
b0 '
b0 /
b0 ;
b0 #
b0 .
b0 9
0(
0&
0$
#655000
b110000001 2
b110000001 8
b110000001 :
01
b1011 A
b0 @
b1010 ,
1$
#660000
b1011 '
b1011 /
b1011 ;
1(
1&
0$
#665000
b1101110 5
b1011 4
b1011 7
b1011 <
1$
#670000
b100 @
b0 '
b0 /
b0 ;
0(
0&
0$
#675000
1$
#680000
b1011 '
b1011 /
b1011 ;
b100 #
b100 .
b100 9
1(
1&
0$
#685000
b1111001 5
b1011 3
b1011 6
b1011 =
1$
#690000
b1 A
b1000 @
b0 '
b0 /
b0 ;
b0 #
b0 .
b0 9
0(
0&
0$
#695000
1$
#700000
b1 '
b1 /
b1 ;
b1000 #
b1000 .
b1000 9
1(
1&
0$
#705000
11
1$
#710000
b111111010 +
b0 '
b0 /
b0 ;
b0 #
b0 .
b0 9
0(
0&
0$
#715000
b111111010 2
b111111010 8
b111111010 :
01
b1100 A
b0 @
b1011 ,
1$
#720000
b1100 '
b1100 /
b1100 ;
1(
1&
0$
#725000
b10000100 5
b1100 4
b1100 7
b1100 <
1$
#730000
b100 @
b0 '
b0 /
b0 ;
0(
0&
0$
#735000
1$
#740000
b1100 '
b1100 /
b1100 ;
b100 #
b100 .
b100 9
1(
1&
0$
#745000
b10010000 5
b1100 3
b1100 6
b1100 =
1$
#750000
b1 A
b1000 @
b0 '
b0 /
b0 ;
b0 #
b0 .
b0 9
0(
0&
0$
#755000
1$
#760000
b1 '
b1 /
b1 ;
b1000 #
b1000 .
b1000 9
1(
1&
0$
#765000
11
1$
#770000
b1010001010 +
b0 '
b0 /
b0 ;
b0 #
b0 .
b0 9
0(
0&
0$
#775000
b1010001010 2
b1010001010 8
b1010001010 :
01
b1101 A
b0 @
b1100 ,
1$
#780000
b1101 '
b1101 /
b1101 ;
1(
1&
0$
#785000
b10011100 5
b1101 4
b1101 7
b1101 <
1$
#790000
b100 @
b0 '
b0 /
b0 ;
0(
0&
0$
#795000
1$
#800000
b1101 '
b1101 /
b1101 ;
b100 #
b100 .
b100 9
1(
1&
0$
#805000
b10101001 5
b1101 3
b1101 6
b1101 =
1$
#810000
b1 A
b1000 @
b0 '
b0 /
b0 ;
b0 #
b0 .
b0 9
0(
0&
0$
#815000
1$
#820000
b1 '
b1 /
b1 ;
b1000 #
b1000 .
b1000 9
1(
1&
0$
#825000
11
1$
#830000
b1100110011 +
b0 '
b0 /
b0 ;
b0 #
b0 .
b0 9
0(
0&
0$
#835000
b1100110011 2
b1100110011 8
b1100110011 :
01
b1110 A
b0 @
b1101 ,
1$
#840000
b1110 '
b1110 /
b1110 ;
1(
1&
0$
#845000
b10110110 5
b1110 4
b1110 7
b1110 <
1$
#850000
b100 @
b0 '
b0 /
b0 ;
0(
0&
0$
#855000
1$
#860000
b1110 '
b1110 /
b1110 ;
b100 #
b100 .
b100 9
1(
1&
0$
#865000
b11000100 5
b1110 3
b1110 6
b1110 =
1$
#870000
b1 A
b1000 @
b0 '
b0 /
b0 ;
b0 #
b0 .
b0 9
0(
0&
0$
#875000
1$
#880000
b1 '
b1 /
b1 ;
b1000 #
b1000 .
b1000 9
1(
1&
0$
#885000
11
1$
#890000
b1111110111 +
b0 '
b0 /
b0 ;
b0 #
b0 .
b0 9
0(
0&
0$
#895000
b1111110111 2
b1111110111 8
b1111110111 :
01
b1111 A
b0 @
b1110 ,
1$
#900000
b1111 '
b1111 /
b1111 ;
1(
1&
0$
#905000
b11010010 5
b1111 4
b1111 7
b1111 <
1$
#910000
b100 @
b0 '
b0 /
b0 ;
0(
0&
0$
#915000
1$
#920000
b1111 '
b1111 /
b1111 ;
b100 #
b100 .
b100 9
1(
1&
0$
#925000
b11100001 5
b1111 3
b1111 6
b1111 =
1$
#930000
b1 A
b1000 @
b0 '
b0 /
b0 ;
b0 #
b0 .
b0 9
0(
0&
0$
#935000
1$
#940000
b1 '
b1 /
b1 ;
b1000 #
b1000 .
b1000 9
1(
1&
0$
#945000
11
1$
#950000
b10011011000 +
b0 '
b0 /
b0 ;
b0 #
b0 .
b0 9
0(
0&
0$
#955000
b10011011000 2
b10011011000 8
b10011011000 :
01
b10000 A
b0 @
b1111 ,
1$
#960000
b10000 '
b10000 /
b10000 ;
1(
1&
0$
#965000
b11110000 5
b10000 4
b10000 7
b10000 <
1$
#970000
b100 @
b0 '
b0 /
b0 ;
0(
0&
0$
#975000
1$
#980000
b10000 '
b10000 /
b10000 ;
b100 #
b100 .
b100 9
1(
1&
0$
#985000
b100000000 5
b10000 3
b10000 6
b10000 =
1$
#990000
b1 A
b1000 @
b0 '
b0 /
b0 ;
b0 #
b0 .
b0 9
0(
0&
0$
#995000
1$
#1000000
b1 '
b1 /
b1 ;
b1000 #
b1000 .
b1000 9
1(
1&
0$
#1005000
11
1$
#1010000
b10111011000 +
b0 '
b0 /
b0 ;
b0 #
b0 .
b0 9
0(
0&
0$
#1015000
b10111011000 2
b10111011000 8
b10111011000 :
01
b10000 ,
1$
#1020000
0$
#1025000
1$
#1030000
0$
#1035000
b1100 ?
1$
#1040000
b1100 #
b1100 .
b1100 9
1&
0$
#1045000
b10111011000 "
b10111011000 0
b10111011000 >
1$
#1050000
b0 #
b0 .
b0 9
0&
0$
#1055000
b1 )
1$
#1060000
1%
0$
#1065000
b0 "
b0 0
b0 >
b0 3
b0 6
b0 =
b0 5
b0 4
b0 7
b0 <
b0 2
b0 8
b0 :
1$
#1070000
0$
#1075000
1$
#1080000
b0 @
b0 ,
b0 +
0%
0$
#1085000
1$
#1090000
b1 '
b1 /
b1 ;
1(
1&
0$
#1095000
b1 4
b1 7
b1 <
1$
#1100000
b10 A
b100 @
b0 '
b0 /
b0 ;
0(
0&
0$
#1105000
1$
#1110000
b10 '
b10 /
b10 ;
b100 #
b100 .
b100 9
1(
1&
0$
#1115000
b10 5
b10 3
b10 6
b10 =
1$
#1120000
b1 A
b1000 @
b0 '
b0 /
b0 ;
b0 #
b0 .
b0 9
0(
0&
0$
#1125000
1$
#1130000
b1 '
b1 /
b1 ;
b1000 #
b1000 .
b1000 9
1(
1&
0$
#1135000
11
1$
#1140000
b10 +
b0 '
b0 /
b0 ;
b0 #
b0 .
b0 9
0(
0&
0$
#1145000
01
b10 2
b10 8
b10 :
b10 A
b0 @
b1 ,
1$
#1150000
b10 '
b10 /
b10 ;
1(
1&
0$
#1155000
b100 5
b10 4
b10 7
b10 <
1$
#1160000
b11 A
b100 @
b0 '
b0 /
b0 ;
0(
0&
0$
#1165000
1$
#1170000
b11 '
b11 /
b11 ;
b100 #
b100 .
b100 9
1(
1&
0$
#1175000
b110 5
b11 3
b11 6
b11 =
1$
#1180000
b1 A
b1000 @
b0 '
b0 /
b0 ;
b0 #
b0 .
b0 9
0(
0&
0$
#1185000
1$
#1190000
b1 '
b1 /
b1 ;
b1000 #
b1000 .
b1000 9
1(
1&
0$
#1195000
11
1$
#1200000
b1000 +
b0 '
b0 /
b0 ;
b0 #
b0 .
b0 9
0(
0&
0$
#1205000
01
b1000 2
b1000 8
b1000 :
b11 A
b0 @
b10 ,
1$
#1210000
b11 '
b11 /
b11 ;
1(
1&
0$
#1215000
b1001 5
b11 4
b11 7
b11 <
1$
#1220000
b100 A
b100 @
b0 '
b0 /
b0 ;
0(
0&
0$
#1225000
1$
#1230000
b100 '
b100 /
b100 ;
b100 #
b100 .
b100 9
1(
1&
0$
#1235000
b1100 5
b100 3
b100 6
b100 =
1$
#1240000
b1 A
b1000 @
b0 '
b0 /
b0 ;
b0 #
b0 .
b0 9
0(
0&
0$
#1245000
1$
#1250000
b1 '
b1 /
b1 ;
b1000 #
b1000 .
b1000 9
1(
1&
0$
#1255000
11
1$
#1260000
b10100 +
b0 '
b0 /
b0 ;
b0 #
b0 .
b0 9
0(
0&
0$
#1265000
01
b10100 2
b10100 8
b10100 :
b100 A
b0 @
b11 ,
1$
#1270000
b100 '
b100 /
b100 ;
1(
1&
0$
#1275000
b10000 5
b100 4
b100 7
b100 <
1$
#1280000
b101 A
b100 @
b0 '
b0 /
b0 ;
0(
0&
0$
#1285000
1$
#1290000
b101 '
b101 /
b101 ;
b100 #
b100 .
b100 9
1(
1&
0$
#1295000
b10100 5
b101 3
b101 6
b101 =
1$
#1300000
b1 A
b1000 @
b0 '
b0 /
b0 ;
b0 #
b0 .
b0 9
0(
0&
0$
#1305000
1$
#1310000
b1 '
b1 /
b1 ;
b1000 #
b1000 .
b1000 9
1(
1&
0$
#1315000
11
1$
#1320000
b101000 +
b0 '
b0 /
b0 ;
b0 #
b0 .
b0 9
0(
0&
0$
#1325000
01
b101000 2
b101000 8
b101000 :
b101 A
b0 @
b100 ,
1$
#1330000
b101 '
b101 /
b101 ;
1(
1&
0$
#1335000
b11001 5
b101 4
b101 7
b101 <
1$
#1340000
b110 A
b100 @
b0 '
b0 /
b0 ;
0(
0&
0$
#1345000
1$
#1350000
b110 '
b110 /
b110 ;
b100 #
b100 .
b100 9
1(
1&
0$
#1355000
b11110 5
b110 3
b110 6
b110 =
1$
#1360000
b1 A
b1000 @
b0 '
b0 /
b0 ;
b0 #
b0 .
b0 9
0(
0&
0$
#1365000
1$
#1370000
b1 '
b1 /
b1 ;
b1000 #
b1000 .
b1000 9
1(
1&
0$
#1375000
11
1$
#1380000
b1000110 +
b0 '
b0 /
b0 ;
b0 #
b0 .
b0 9
0(
0&
0$
#1385000
01
b1000110 2
b1000110 8
b1000110 :
b110 A
b0 @
b101 ,
1$
#1390000
b110 '
b110 /
b110 ;
1(
1&
0$
#1395000
b100100 5
b110 4
b110 7
b110 <
1$
#1400000
b111 A
b100 @
b0 '
b0 /
b0 ;
0(
0&
0$
#1405000
1$
#1410000
b111 '
b111 /
b111 ;
b100 #
b100 .
b100 9
1(
1&
0$
#1415000
b101010 5
b111 3
b111 6
b111 =
1$
#1420000
b1 A
b1000 @
b0 '
b0 /
b0 ;
b0 #
b0 .
b0 9
0(
0&
0$
#1425000
1$
#1430000
b1 '
b1 /
b1 ;
b1000 #
b1000 .
b1000 9
1(
1&
0$
#1435000
11
1$
#1440000
b1110000 +
b0 '
b0 /
b0 ;
b0 #
b0 .
b0 9
0(
0&
0$
#1445000
01
b1110000 2
b1110000 8
b1110000 :
b111 A
b0 @
b110 ,
1$
#1450000
b111 '
b111 /
b111 ;
1(
1&
0$
#1455000
b110001 5
b111 4
b111 7
b111 <
1$
#1460000
b1000 A
b100 @
b0 '
b0 /
b0 ;
0(
0&
0$
#1465000
1$
#1470000
b1000 '
b1000 /
b1000 ;
b100 #
b100 .
b100 9
1(
1&
0$
#1475000
b111000 5
b1000 3
b1000 6
b1000 =
1$
#1480000
b1 A
b1000 @
b0 '
b0 /
b0 ;
b0 #
b0 .
b0 9
0(
0&
0$
#1485000
1$
#1490000
b1 '
b1 /
b1 ;
b1000 #
b1000 .
b1000 9
1(
1&
0$
#1495000
11
1$
#1500000
b10101000 +
b0 '
b0 /
b0 ;
b0 #
b0 .
b0 9
0(
0&
0$
#1505000
01
b10101000 2
b10101000 8
b10101000 :
b1000 A
b0 @
b111 ,
1$
#1510000
b1000 '
b1000 /
b1000 ;
1(
1&
0$
#1515000
b1000000 5
b1000 4
b1000 7
b1000 <
1$
#1520000
b1001 A
b100 @
b0 '
b0 /
b0 ;
0(
0&
0$
#1525000
1$
#1530000
b1001 '
b1001 /
b1001 ;
b100 #
b100 .
b100 9
1(
1&
0$
#1535000
b1001000 5
b1001 3
b1001 6
b1001 =
1$
#1540000
b1 A
b1000 @
b0 '
b0 /
b0 ;
b0 #
b0 .
b0 9
0(
0&
0$
#1545000
1$
#1550000
b1 '
b1 /
b1 ;
b1000 #
b1000 .
b1000 9
1(
1&
0$
#1555000
11
1$
#1560000
b11110000 +
b0 '
b0 /
b0 ;
b0 #
b0 .
b0 9
0(
0&
0$
#1565000
01
b11110000 2
b11110000 8
b11110000 :
b1001 A
b0 @
b1000 ,
1$
#1570000
b1001 '
b1001 /
b1001 ;
1(
1&
0$
#1575000
b1010001 5
b1001 4
b1001 7
b1001 <
1$
#1580000
b1010 A
b100 @
b0 '
b0 /
b0 ;
0(
0&
0$
#1585000
1$
#1590000
b1010 '
b1010 /
b1010 ;
b100 #
b100 .
b100 9
1(
1&
0$
#1595000
b1011010 5
b1010 3
b1010 6
b1010 =
1$
#1600000
b1 A
b1000 @
b0 '
b0 /
b0 ;
b0 #
b0 .
b0 9
0(
0&
0$
#1605000
1$
#1610000
b1 '
b1 /
b1 ;
b1000 #
b1000 .
b1000 9
1(
1&
0$
#1615000
11
1$
#1620000
b101001010 +
b0 '
b0 /
b0 ;
b0 #
b0 .
b0 9
0(
0&
0$
#1625000
01
b101001010 2
b101001010 8
b101001010 :
b1010 A
b0 @
b1001 ,
1$
#1630000
b1010 '
b1010 /
b1010 ;
1(
1&
0$
#1635000
b1100100 5
b1010 4
b1010 7
b1010 <
1$
#1640000
b1011 A
b100 @
b0 '
b0 /
b0 ;
0(
0&
0$
#1645000
1$
