project/m4/rtl/compute_core.sv
/*
 * Module: compute_core
 *
 * Purpose:
 *   Simple INT8 multiply-accumulate compute core for the HW4AI M4 project.
 *   This represents the dominant GEMM/MAC operation from the project.
 *
 * Ports:
 *   clk    : input,  1 bit   - clock
 *   rst    : input,  1 bit   - active-high synchronous reset
 *   valid  : input,  1 bit   - when high, input a and b are accumulated
 *   a      : input,  8 bits  - signed INT8 operand A
 *   b      : input,  8 bits  - signed INT8 operand B
 *   out    : output, 32 bits - signed accumulated MAC result
 *
 * Clocking:
 *   Single clock domain using clk.
 *
 * Reset:
 *   Active-high synchronous reset. When rst = 1, out is cleared to 0.
 */

module compute_core (
    input  logic clk,
    input  logic rst,
    input  logic valid,
    input  logic signed [7:0] a,
    input  logic signed [7:0] b,
    output logic signed [31:0] out
);

    logic signed [15:0] product;

    assign product = a * b;

    always_ff @(posedge clk) begin
        if (rst) begin
            out <= 32'sd0;
        end else if (valid) begin
            out <= out + {{16{product[15]}}, product};
        end
    end

endmodule

project/m4/rtl/interface_ctrl.sv
/*
 * Module: interface_ctrl
 *
 * Purpose:
 *   Memory-mapped interface to control compute_core.
 *
 * Protocol:
 *   Simple valid/ready handshake (always-ready).
 *
 * Register Map:
 *   0x00 : operand A
 *   0x04 : operand B
 *   0x08 : control (bit[0] = start)
 *   0x0C : result
 *
 * Ports:
 *   clk        : clock
 *   rst        : active-high synchronous reset
 *   valid      : request valid
 *   ready      : always ready
 *   write      : write enable
 *   addr       : address
 *   wdata      : write data
 *   rdata      : read data
 *   core_valid : trigger to compute core
 *   core_a     : operand A
 *   core_b     : operand B
 *   core_out   : result from compute core
 */



module interface_ctrl (
    input  wire clk,
    input  wire rst,

    input  wire valid,
    output wire ready,
    input  wire write,
    input  wire [7:0] addr,
    input  wire [31:0] wdata,
    output reg  [31:0] rdata,

    output reg  core_valid,
    output reg  signed [7:0] core_a,
    output reg  signed [7:0] core_b,
    input  wire signed [31:0] core_out
);

    assign ready = 1'b1;

    always @(posedge clk) begin
        if (rst) begin
            core_a     <= 0;
            core_b     <= 0;
            core_valid <= 0;
            rdata      <= 0;
        end else begin
            core_valid <= 0;

            if (valid && ready) begin
                if (write) begin
                    case (addr)
                        8'h00: core_a <= wdata[7:0];
                        8'h04: core_b <= wdata[7:0];
                        8'h08: begin
                            if (wdata[0])
                                core_valid <= 1;
                        end
                    endcase
                end else begin
                    case (addr)
                        8'h00: rdata <= {{24{core_a[7]}}, core_a};
                        8'h04: rdata <= {{24{core_b[7]}}, core_b};
                        8'h0C: rdata <= core_out;
                        default: rdata <= 0;
                    endcase
                end
            end
        end
    end

endmodule

project/m4/rtl/top.sv
/*
 * Module: top
 *
 * Purpose:
 *   M3 integrated top module connecting the memory-mapped interface
 *   to the INT8 MAC compute core.
 *
 * Ports:
 *   clk   : input,  1 bit   - clock
 *   rst   : input,  1 bit   - active-high reset
 *   valid : input,  1 bit   - host request valid
 *   ready : output, 1 bit   - interface ready
 *   write : input,  1 bit   - host write enable
 *   addr  : input,  8 bits  - memory-mapped address
 *   wdata : input,  32 bits - host write data
 *   rdata : output, 32 bits - host read data
 *
 * Glue logic:
 *   No extra FIFO or clock-domain crossing is used.
 *   The interface directly drives core_valid, core_a, and core_b.
 *   The compute result core_out is returned back through the interface.
 */

module top (
    input  wire clk,
    input  wire rst,

    input  wire valid,
    output wire ready,
    input  wire write,

    input  wire [7:0]  addr,
    input  wire [31:0] wdata,
    output wire [31:0] rdata
);

    wire core_valid;
    wire signed [7:0] core_a;
    wire signed [7:0] core_b;
    wire signed [31:0] core_out;

    interface_ctrl u_interface (
        .clk(clk),
        .rst(rst),
        .valid(valid),
        .ready(ready),
        .write(write),
        .addr(addr),
        .wdata(wdata),
        .rdata(rdata),
        .core_valid(core_valid),
        .core_a(core_a),
        .core_b(core_b),
        .core_out(core_out)
    );

    compute_core u_compute (
        .clk(clk),
        .rst(rst),
        .valid(core_valid),
        .a(core_a),
        .b(core_b),
        .out(core_out)
    );

endmodule

project/m3/tb/tb_top.sv
`timescale 1ns/1ps

module tb_top;

    logic clk;
    logic rst;

    logic valid;
    logic ready;
    logic write;
    logic [7:0] addr;
    logic [31:0] wdata;
    logic [31:0] rdata;

    top dut (
        .clk(clk),
        .rst(rst),
        .valid(valid),
        .ready(ready),
        .write(write),
        .addr(addr),
        .wdata(wdata),
        .rdata(rdata)
    );

    always #5 clk = ~clk;

    task host_write(input [7:0] write_addr, input [31:0] write_data);
        begin
            @(negedge clk);
            valid = 1'b1;
            write = 1'b1;
            addr  = write_addr;
            wdata = write_data;

            @(negedge clk);
            valid = 1'b0;
            write = 1'b0;
            addr  = 8'h00;
            wdata = 32'h00000000;
        end
    endtask

    task host_read(input [7:0] read_addr);
        begin
            @(negedge clk);
            valid = 1'b1;
            write = 1'b0;
            addr  = read_addr;

            @(negedge clk);
            valid = 1'b0;
            addr  = 8'h00;
        end
    endtask

    initial begin
        $dumpfile("project/m3/sim/cosim_waveform.vcd");
        $dumpvars(0, tb_top);

        clk = 0;
        rst = 1;
        valid = 0;
        write = 0;
        addr = 0;
        wdata = 0;

        repeat (3) @(posedge clk);
        rst = 0;

        // End-to-end host transaction:
        // A = 3, B = 4, expected MAC result = 12
        host_write(8'h00, 32'd3);
        host_write(8'h04, 32'd4);
        host_write(8'h08, 32'd1);

        repeat (3) @(posedge clk);

        host_read(8'h0C);

        @(posedge clk);

        $display("Expected result = 12");
        $display("DUT result      = %0d", $signed(rdata));

        if ($signed(rdata) == 32'sd12) begin
            $display("PASS: End-to-end host-interface-compute-host test passed");
        end else begin
            $display("FAIL: End-to-end test failed");
        end

        #20;
        $finish;
    end

endmodule

project/m3/sim/cosim_waveform.vcd
$date
	Thu May 21 17:53:00 2026
$end
$version
	Icarus Verilog
$end
$timescale
	1ps
$end
$scope module tb_top $end
$var wire 1 ! ready $end
$var wire 32 " rdata [31:0] $end
$var reg 8 # addr [7:0] $end
$var reg 1 $ clk $end
$var reg 1 % rst $end
$var reg 1 & valid $end
$var reg 32 ' wdata [31:0] $end
$var reg 1 ( write $end
$scope module dut $end
$var wire 8 ) addr [7:0] $end
$var wire 1 $ clk $end
$var wire 1 ! ready $end
$var wire 1 % rst $end
$var wire 1 & valid $end
$var wire 32 * wdata [31:0] $end
$var wire 1 ( write $end
$var wire 32 + rdata [31:0] $end
$var wire 1 , core_valid $end
$var wire 32 - core_out [31:0] $end
$var wire 8 . core_b [7:0] $end
$var wire 8 / core_a [7:0] $end
$scope module u_compute $end
$var wire 1 $ clk $end
$var wire 1 % rst $end
$var wire 1 , valid $end
$var wire 16 0 product [15:0] $end
$var wire 8 1 b [7:0] $end
$var wire 8 2 a [7:0] $end
$var reg 32 3 out [31:0] $end
$upscope $end
$scope module u_interface $end
$var wire 8 4 addr [7:0] $end
$var wire 1 $ clk $end
$var wire 32 5 core_out [31:0] $end
$var wire 1 ! ready $end
$var wire 1 % rst $end
$var wire 1 & valid $end
$var wire 32 6 wdata [31:0] $end
$var wire 1 ( write $end
$var reg 8 7 core_a [7:0] $end
$var reg 8 8 core_b [7:0] $end
$var reg 1 , core_valid $end
$var reg 32 9 rdata [31:0] $end
$upscope $end
$upscope $end
$scope task host_read $end
$var reg 8 : read_addr [7:0] $end
$upscope $end
$scope task host_write $end
$var reg 8 ; write_addr [7:0] $end
$var reg 32 < write_data [31:0] $end
$upscope $end
$upscope $end
$enddefinitions $end
#0
$dumpvars
bx <
bx ;
bx :
bx 9
bx 8
bx 7
b0 6
bx 5
b0 4
bx 3
bx 2
bx 1
bx 0
bx /
bx .
bx -
x,
bx +
b0 *
b0 )
0(
b0 '
0&
1%
0$
b0 #
bx "
1!
$end
#5000
b0 "
b0 +
b0 9
0,
b0 0
b0 .
b0 1
b0 8
b0 /
b0 2
b0 7
b0 -
b0 3
b0 5
1$
#10000
0$
#15000
1$
#20000
0$
#25000
b11 <
b0 ;
0%
1$
#30000
b11 '
b11 *
b11 6
1(
1&
0$
#35000
b11 /
b11 2
b11 7
1$
#40000
b100 <
b100 ;
b0 '
b0 *
b0 6
0(
0&
0$
#45000
1$
#50000
b100 '
b100 *
b100 6
b100 #
b100 )
b100 4
1(
1&
0$
#55000
b1100 0
b100 .
b100 1
b100 8
1$
#60000
b1 <
b1000 ;
b0 '
b0 *
b0 6
b0 #
b0 )
b0 4
0(
0&
0$
#65000
1$
#70000
b1 '
b1 *
b1 6
b1000 #
b1000 )
b1000 4
1(
1&
0$
#75000
1,
1$
#80000
b0 '
b0 *
b0 6
b0 #
b0 )
b0 4
0(
0&
0$
#85000
0,
b1100 -
b1100 3
b1100 5
1$
#90000
0$
#95000
1$
#100000
0$
#105000
b1100 :
1$
#110000
b1100 #
b1100 )
b1100 4
1&
0$
#115000
b1100 "
b1100 +
b1100 9
1$
#120000
b0 #
b0 )
b0 4
0&
0$
